dataclass_dsl/__init__.py
dataclass_dsl/_attr_ref.py
dataclass_dsl/_cli.py
dataclass_dsl/_codegen.py
dataclass_dsl/_decorator.py
dataclass_dsl/_inspect.py
dataclass_dsl/_ir.py
dataclass_dsl/_loader.py
dataclass_dsl/_metaclass.py
dataclass_dsl/_ordering.py
dataclass_dsl/_property_type.py
dataclass_dsl/_provider.py
dataclass_dsl/_registry.py
dataclass_dsl/_resource.py
dataclass_dsl/_serialization.py
dataclass_dsl/_stubs.py
dataclass_dsl/_template.py
dataclass_dsl/_types.py
dataclass_dsl/_utils.py
dataclass_dsl/py.typed
dataclass_dsl/_importer/__init__.py
dataclass_dsl/_importer/topology.py
dataclass_dsl-1.1.1.dist-info/METADATA
dataclass_dsl-1.1.1.dist-info/WHEEL
dataclass_dsl-1.1.1.dist-info/licenses/LICENSE
dataclass_dsl-1.1.1.dist-info/RECORD
