Metadata-Version: 2.4
Name: dataclass-dsl
Version: 1.1.1
Summary: Dataclass runtime machinery for declarative DSLs
Project-URL: Homepage, https://github.com/lex00/dataclass-dsl
Project-URL: Documentation, https://github.com/lex00/dataclass-dsl#readme
Project-URL: Repository, https://github.com/lex00/dataclass-dsl
Project-URL: Issues, https://github.com/lex00/dataclass-dsl/issues
Author-email: Alex Artigues <albert.a.artigues@gmail.com>
License: MIT
License-File: LICENSE
Keywords: configuration,dataclasses,declarative,dsl,graph,infrastructure,references,typing
Classifier: Development Status :: 5 - Production/Stable
Classifier: Intended Audience :: Developers
Classifier: License :: OSI Approved :: MIT License
Classifier: Programming Language :: Python :: 3
Classifier: Programming Language :: Python :: 3.11
Classifier: Programming Language :: Python :: 3.12
Classifier: Programming Language :: Python :: 3.13
Classifier: Programming Language :: Python :: 3.14
Classifier: Topic :: Software Development :: Libraries :: Python Modules
Classifier: Typing :: Typed
Requires-Python: >=3.11
Provides-Extra: dev
Requires-Dist: pytest-cov>=4.1; extra == 'dev'
Requires-Dist: pytest>=7.4; extra == 'dev'
Requires-Dist: ruff>=0.1; extra == 'dev'
Requires-Dist: ty>=0.0.1a0; extra == 'dev'
